lanka_data/__init__.py
lanka_data_nuuuwan-1.0.0.dist-info/LICENSE
lanka_data_nuuuwan-1.0.0.dist-info/METADATA
lanka_data_nuuuwan-1.0.0.dist-info/WHEEL
lanka_data_nuuuwan-1.0.0.dist-info/top_level.txt
lanka_data_nuuuwan-1.0.0.dist-info/RECORD
