Metadata-Version: 2.1
Name: lanka-data-nuuuwan
Version: 1.0.0
Summary: A collection of utility functions for interacting with Public Data about Sri Lanka.
Home-page: https://github.com/nuuuwan/lanka_data
Author: Nuwan I. Senaratna
Author-email: nuuuwan@gmail.com
Project-URL: Bug Tracker, https://github.com/nuuuwan/lanka_data/issues
Classifier: Programming Language :: Python :: 3
Classifier: License :: OSI Approved :: MIT License
Classifier: Operating System :: OS Independent
Requires-Python: >=3.10
License-File: LICENSE
Requires-Dist: utils-nuuuwan
